[{"commodity_item_id":33,"new_price":7413.0,"update_at":"2023-04-25 17:30:47"},{"commodity_item_id":59,"new_price":9529.0,"update_at":"2023-05-29 11:43:19"},{"commodity_item_id":5,"new_price":4695.0,"update_at":"2023-07-30 14:30:07"},{"commodity_item_id":83,"new_price":8734.0,"update_at":"2023-03-01 22:31:18"},{"commodity_item_id":16,"new_price":3611.0,"update_at":"2023-08-01 06:14:10"},{"commodity_item_id":35,"new_price":7740.0,"update_at":"2023-10-21 08:10:34"},{"commodity_item_id":63,"new_price":9959.0,"update_at":"2023-11-21 03:39:34"},{"commodity_item_id":67,"new_price":8604.0,"update_at":"2023-01-31 02:24:28"},{"commodity_item_id":89,"new_price":6806.0,"update_at":"2023-10-15 20:37:14"},{"commodity_item_id":60,"new_price":8944.0,"update_at":"2023-05-27 13:01:45"},{"commodity_item_id":43,"new_price":2521.0,"update_at":"2023-07-26 22:42:14"},{"commodity_item_id":65,"new_price":9939.0,"update_at":"2023-11-17 12:18:45"},{"commodity_item_id":94,"new_price":8492.0,"update_at":"2023-05-11 13:31:45"},{"commodity_item_id":53,"new_price":1161.0,"update_at":"2023-09-15 15:34:59"},{"commodity_item_id":31,"new_price":3902.0,"update_at":"2023-09-24 13:54:55"},{"commodity_item_id":49,"new_price":789.0,"update_at":"2023-06-10 12:33:16"},{"commodity_item_id":39,"new_price":1060.0,"update_at":"2023-06-18 22:56:54"},{"commodity_item_id":76,"new_price":2521.0,"update_at":"2023-09-01 23:47:11"},{"commodity_item_id":57,"new_price":3065.0,"update_at":"2023-01-23 12:20:03"},{"commodity_item_id":19,"new_price":4797.0,"update_at":"2023-08-08 16:56:25"},{"commodity_item_id":78,"new_price":764.0,"update_at":"2023-04-03 05:14:36"},{"commodity_item_id":46,"new_price":217.0,"update_at":"2023-11-22 15:43:00"},{"commodity_item_id":84,"new_price":5537.0,"update_at":"2023-11-09 16:57:30"},{"commodity_item_id":55,"new_price":7968.0,"update_at":"2023-03-04 15:42:21"},{"commodity_item_id":68,"new_price":8575.0,"update_at":"2023-06-16 07:45:11"},{"commodity_item_id":83,"new_price":2869.0,"update_at":"2023-10-16 16:14:11"},{"commodity_item_id":34,"new_price":1408.0,"update_at":"2023-07-25 02:22:35"},{"commodity_item_id":26,"new_price":1758.0,"update_at":"2023-03-13 05:38:41"},{"commodity_item_id":26,"new_price":4007.0,"update_at":"2023-07-05 22:21:12"},{"commodity_item_id":82,"new_price":4375.0,"update_at":"2023-05-07 13:19:34"},{"commodity_item_id":98,"new_price":6454.0,"update_at":"2023-03-30 07:40:19"},{"commodity_item_id":33,"new_price":4730.0,"update_at":"2023-04-02 18:25:23"},{"commodity_item_id":33,"new_price":8268.0,"update_at":"2023-03-24 21:33:10"},{"commodity_item_id":93,"new_price":8328.0,"update_at":"2023-09-30 11:02:20"},{"commodity_item_id":53,"new_price":1705.0,"update_at":"2023-02-18 12:52:58"},{"commodity_item_id":78,"new_price":2058.0,"update_at":"2023-06-02 15:58:44"},{"commodity_item_id":68,"new_price":3145.0,"update_at":"2023-05-31 13:07:38"},{"commodity_item_id":58,"new_price":4336.0,"update_at":"2023-09-08 14:20:14"},{"commodity_item_id":17,"new_price":1927.0,"update_at":"2023-04-27 01:57:03"},{"commodity_item_id":13,"new_price":2332.0,"update_at":"2023-02-14 12:08:30"},{"commodity_item_id":94,"new_price":2965.0,"update_at":"2023-06-14 15:21:45"},{"commodity_item_id":24,"new_price":6806.0,"update_at":"2023-01-07 23:57:23"},{"commodity_item_id":81,"new_price":2973.0,"update_at":"2023-09-13 20:11:20"},{"commodity_item_id":31,"new_price":1068.0,"update_at":"2023-03-02 02:38:15"},{"commodity_item_id":1,"new_price":105.0,"update_at":"2023-09-07 17:12:34"},{"commodity_item_id":55,"new_price":9932.0,"update_at":"2023-10-10 18:12:54"},{"commodity_item_id":13,"new_price":3842.0,"update_at":"2023-05-06 05:08:34"},{"commodity_item_id":78,"new_price":5229.0,"update_at":"2023-11-05 23:03:02"},{"commodity_item_id":76,"new_price":8684.0,"update_at":"2023-01-14 04:08:13"},{"commodity_item_id":50,"new_price":8330.0,"update_at":"2023-08-12 02:04:34"},{"commodity_item_id":92,"new_price":604.0,"update_at":"2023-01-06 21:01:50"},{"commodity_item_id":39,"new_price":590.0,"update_at":"2023-11-10 01:09:30"},{"commodity_item_id":59,"new_price":2976.0,"update_at":"2023-01-26 01:20:32"},{"commodity_item_id":55,"new_price":9507.0,"update_at":"2023-03-22 10:55:48"},{"commodity_item_id":86,"new_price":6378.0,"update_at":"2023-11-26 21:42:08"},{"commodity_item_id":59,"new_price":4548.0,"update_at":"2023-08-28 12:55:11"},{"commodity_item_id":70,"new_price":4606.0,"update_at":"2023-04-20 11:35:03"},{"commodity_item_id":17,"new_price":2907.0,"update_at":"2023-04-19 14:13:58"},{"commodity_item_id":79,"new_price":8582.0,"update_at":"2023-11-03 09:37:03"},{"commodity_item_id":93,"new_price":281.0,"update_at":"2023-09-09 23:01:07"},{"commodity_item_id":62,"new_price":8789.0,"update_at":"2023-08-12 05:47:46"},{"commodity_item_id":48,"new_price":6853.0,"update_at":"2023-04-11 19:54:00"},{"commodity_item_id":43,"new_price":7674.0,"update_at":"2023-05-25 03:51:46"},{"commodity_item_id":64,"new_price":2049.0,"update_at":"2023-06-05 00:18:17"},{"commodity_item_id":73,"new_price":2552.0,"update_at":"2023-08-30 05:40:22"},{"commodity_item_id":67,"new_price":1989.0,"update_at":"2023-01-14 01:49:07"},{"commodity_item_id":10,"new_price":3449.0,"update_at":"2023-07-16 22:40:04"},{"commodity_item_id":37,"new_price":9505.0,"update_at":"2023-07-30 06:25:27"},{"commodity_item_id":55,"new_price":9376.0,"update_at":"2023-06-24 03:04:46"},{"commodity_item_id":89,"new_price":9882.0,"update_at":"2023-03-23 18:44:22"},{"commodity_item_id":100,"new_price":3317.0,"update_at":"2023-08-10 19:17:31"},{"commodity_item_id":33,"new_price":6389.0,"update_at":"2023-08-31 21:15:11"},{"commodity_item_id":49,"new_price":9910.0,"update_at":"2023-06-02 20:35:55"},{"commodity_item_id":20,"new_price":6296.0,"update_at":"2023-11-23 13:29:07"},{"commodity_item_id":78,"new_price":8581.0,"update_at":"2023-09-05 22:13:46"},{"commodity_item_id":48,"new_price":1341.0,"update_at":"2023-10-30 10:41:07"},{"commodity_item_id":43,"new_price":5259.0,"update_at":"2023-09-24 19:43:33"},{"commodity_item_id":37,"new_price":6189.0,"update_at":"2023-10-08 14:49:36"},{"commodity_item_id":33,"new_price":2319.0,"update_at":"2023-11-05 14:45:17"},{"commodity_item_id":81,"new_price":954.0,"update_at":"2023-02-22 20:27:49"},{"commodity_item_id":77,"new_price":1673.0,"update_at":"2023-06-26 13:31:09"},{"commodity_item_id":61,"new_price":7749.0,"update_at":"2023-11-04 02:44:43"},{"commodity_item_id":34,"new_price":1034.0,"update_at":"2023-05-27 09:58:11"},{"commodity_item_id":71,"new_price":3001.0,"update_at":"2023-07-04 07:46:14"},{"commodity_item_id":23,"new_price":3661.0,"update_at":"2023-04-13 14:52:55"},{"commodity_item_id":38,"new_price":6088.0,"update_at":"2023-03-06 11:32:58"},{"commodity_item_id":79,"new_price":9932.0,"update_at":"2023-05-17 20:31:12"},{"commodity_item_id":93,"new_price":6756.0,"update_at":"2023-11-03 22:53:17"},{"commodity_item_id":66,"new_price":3855.0,"update_at":"2023-07-24 07:09:10"},{"commodity_item_id":27,"new_price":9377.0,"update_at":"2023-04-10 18:33:08"},{"commodity_item_id":56,"new_price":6874.0,"update_at":"2023-10-01 19:24:05"},{"commodity_item_id":57,"new_price":3076.0,"update_at":"2023-08-16 14:24:11"},{"commodity_item_id":87,"new_price":4182.0,"update_at":"2023-03-09 21:21:05"},{"commodity_item_id":85,"new_price":3690.0,"update_at":"2023-03-07 14:07:32"},{"commodity_item_id":75,"new_price":8614.0,"update_at":"2023-10-21 13:14:05"},{"commodity_item_id":18,"new_price":6874.0,"update_at":"2023-07-27 05:58:52"},{"commodity_item_id":51,"new_price":9268.0,"update_at":"2023-08-20 06:27:12"},{"commodity_item_id":83,"new_price":2915.0,"update_at":"2023-06-13 05:00:56"},{"commodity_item_id":64,"new_price":6327.0,"update_at":"2023-11-20 03:51:53"},{"commodity_item_id":24,"new_price":4592.0,"update_at":"2023-10-12 08:53:26"},{"commodity_item_id":80,"new_price":7072.0,"update_at":"2023-06-23 02:34:11"},{"commodity_item_id":59,"new_price":9381.0,"update_at":"2023-04-06 18:24:41"},{"commodity_item_id":88,"new_price":539.0,"update_at":"2023-09-28 11:31:44"},{"commodity_item_id":6,"new_price":7954.0,"update_at":"2023-09-26 07:04:08"},{"commodity_item_id":19,"new_price":7913.0,"update_at":"2023-04-08 22:54:38"},{"commodity_item_id":20,"new_price":3637.0,"update_at":"2023-08-16 00:57:54"},{"commodity_item_id":29,"new_price":9311.0,"update_at":"2023-06-06 18:53:27"},{"commodity_item_id":49,"new_price":6396.0,"update_at":"2023-07-07 04:07:34"},{"commodity_item_id":37,"new_price":679.0,"update_at":"2023-02-15 04:15:51"},{"commodity_item_id":6,"new_price":4132.0,"update_at":"2023-01-02 12:23:01"},{"commodity_item_id":9,"new_price":2459.0,"update_at":"2023-10-07 15:22:14"},{"commodity_item_id":12,"new_price":507.0,"update_at":"2023-11-13 15:43:26"},{"commodity_item_id":85,"new_price":1041.0,"update_at":"2023-04-16 20:52:28"},{"commodity_item_id":81,"new_price":4181.0,"update_at":"2023-07-29 03:46:54"},{"commodity_item_id":44,"new_price":7688.0,"update_at":"2023-09-14 01:05:34"},{"commodity_item_id":57,"new_price":458.0,"update_at":"2023-10-27 18:20:39"},{"commodity_item_id":86,"new_price":3654.0,"update_at":"2023-01-21 04:58:21"},{"commodity_item_id":32,"new_price":1104.0,"update_at":"2023-03-23 16:55:28"},{"commodity_item_id":41,"new_price":3274.0,"update_at":"2023-03-20 23:06:33"},{"commodity_item_id":96,"new_price":3459.0,"update_at":"2023-02-05 04:43:54"},{"commodity_item_id":43,"new_price":6546.0,"update_at":"2023-08-06 02:05:02"},{"commodity_item_id":45,"new_price":7690.0,"update_at":"2023-05-11 01:04:21"},{"commodity_item_id":29,"new_price":5090.0,"update_at":"2023-10-08 16:22:16"},{"commodity_item_id":90,"new_price":7231.0,"update_at":"2023-05-11 00:17:05"},{"commodity_item_id":65,"new_price":4523.0,"update_at":"2023-07-27 15:49:07"},{"commodity_item_id":56,"new_price":1411.0,"update_at":"2023-04-04 17:22:20"},{"commodity_item_id":85,"new_price":7805.0,"update_at":"2023-05-27 18:22:36"},{"commodity_item_id":30,"new_price":9120.0,"update_at":"2023-03-18 09:32:55"},{"commodity_item_id":94,"new_price":7435.0,"update_at":"2023-10-08 07:02:43"},{"commodity_item_id":84,"new_price":1603.0,"update_at":"2023-04-07 20:01:19"},{"commodity_item_id":25,"new_price":680.0,"update_at":"2023-01-04 10:33:41"},{"commodity_item_id":76,"new_price":211.0,"update_at":"2023-11-20 02:44:37"},{"commodity_item_id":30,"new_price":2099.0,"update_at":"2023-02-06 09:52:42"},{"commodity_item_id":19,"new_price":2660.0,"update_at":"2023-04-20 22:55:55"},{"commodity_item_id":20,"new_price":8871.0,"update_at":"2023-08-15 20:16:25"},{"commodity_item_id":81,"new_price":2758.0,"update_at":"2023-05-09 06:33:26"},{"commodity_item_id":98,"new_price":9633.0,"update_at":"2023-09-14 18:39:03"},{"commodity_item_id":62,"new_price":16.0,"update_at":"2023-10-14 15:44:05"},{"commodity_item_id":90,"new_price":4940.0,"update_at":"2023-02-10 12:47:29"},{"commodity_item_id":48,"new_price":7810.0,"update_at":"2023-08-10 22:17:54"},{"commodity_item_id":51,"new_price":5951.0,"update_at":"2023-06-16 17:51:20"},{"commodity_item_id":20,"new_price":5790.0,"update_at":"2023-04-17 16:33:55"},{"commodity_item_id":37,"new_price":2593.0,"update_at":"2023-01-10 20:16:48"},{"commodity_item_id":1,"new_price":2249.0,"update_at":"2023-09-20 19:55:16"},{"commodity_item_id":8,"new_price":8782.0,"update_at":"2023-11-17 01:00:10"},{"commodity_item_id":13,"new_price":1937.0,"update_at":"2023-01-06 07:44:51"},{"commodity_item_id":51,"new_price":3074.0,"update_at":"2023-04-13 14:25:09"},{"commodity_item_id":33,"new_price":3918.0,"update_at":"2023-05-30 06:00:04"},{"commodity_item_id":4,"new_price":29.0,"update_at":"2023-08-10 01:10:03"},{"commodity_item_id":93,"new_price":5364.0,"update_at":"2023-09-11 00:33:50"},{"commodity_item_id":70,"new_price":9600.0,"update_at":"2023-01-04 19:51:26"},{"commodity_item_id":26,"new_price":3836.0,"update_at":"2023-11-01 03:56:14"},{"commodity_item_id":40,"new_price":6362.0,"update_at":"2023-02-03 02:55:31"},{"commodity_item_id":5,"new_price":7530.0,"update_at":"2023-02-08 12:57:23"},{"commodity_item_id":11,"new_price":7730.0,"update_at":"2023-03-02 11:44:48"},{"commodity_item_id":54,"new_price":8391.0,"update_at":"2023-02-02 03:27:42"},{"commodity_item_id":7,"new_price":8976.0,"update_at":"2023-04-27 00:48:48"},{"commodity_item_id":55,"new_price":8926.0,"update_at":"2023-05-16 00:35:51"},{"commodity_item_id":92,"new_price":3843.0,"update_at":"2023-06-23 20:06:12"},{"commodity_item_id":39,"new_price":3526.0,"update_at":"2023-07-26 02:25:19"},{"commodity_item_id":1,"new_price":8239.0,"update_at":"2023-11-10 21:07:50"},{"commodity_item_id":40,"new_price":33.0,"update_at":"2023-03-20 05:57:24"},{"commodity_item_id":75,"new_price":6284.0,"update_at":"2023-02-22 14:09:45"},{"commodity_item_id":29,"new_price":9918.0,"update_at":"2023-07-15 17:01:59"},{"commodity_item_id":55,"new_price":9774.0,"update_at":"2023-07-12 07:44:27"},{"commodity_item_id":24,"new_price":5021.0,"update_at":"2023-04-04 03:35:17"},{"commodity_item_id":74,"new_price":96.0,"update_at":"2023-01-31 13:48:23"},{"commodity_item_id":85,"new_price":7415.0,"update_at":"2023-03-05 21:11:08"},{"commodity_item_id":99,"new_price":3346.0,"update_at":"2023-08-01 22:21:50"},{"commodity_item_id":60,"new_price":6080.0,"update_at":"2023-09-18 03:44:47"},{"commodity_item_id":43,"new_price":2076.0,"update_at":"2023-01-07 18:30:00"},{"commodity_item_id":88,"new_price":8541.0,"update_at":"2023-01-31 08:55:49"},{"commodity_item_id":31,"new_price":4489.0,"update_at":"2023-03-07 11:54:32"},{"commodity_item_id":66,"new_price":9883.0,"update_at":"2023-11-25 08:01:02"},{"commodity_item_id":61,"new_price":5536.0,"update_at":"2023-05-06 00:21:16"},{"commodity_item_id":72,"new_price":8394.0,"update_at":"2023-06-09 09:18:28"},{"commodity_item_id":99,"new_price":575.0,"update_at":"2023-04-29 09:01:26"},{"commodity_item_id":60,"new_price":9790.0,"update_at":"2023-05-05 08:21:59"},{"commodity_item_id":72,"new_price":8744.0,"update_at":"2023-05-15 01:30:11"},{"commodity_item_id":83,"new_price":8087.0,"update_at":"2023-07-27 01:39:38"},{"commodity_item_id":31,"new_price":2196.0,"update_at":"2023-08-07 15:55:35"},{"commodity_item_id":70,"new_price":5638.0,"update_at":"2023-11-25 21:34:19"},{"commodity_item_id":71,"new_price":1039.0,"update_at":"2023-11-19 02:38:02"},{"commodity_item_id":85,"new_price":3589.0,"update_at":"2023-03-12 23:01:28"},{"commodity_item_id":60,"new_price":4510.0,"update_at":"2023-08-23 01:01:34"},{"commodity_item_id":92,"new_price":5945.0,"update_at":"2023-03-08 02:59:29"},{"commodity_item_id":100,"new_price":6844.0,"update_at":"2023-08-08 06:55:36"},{"commodity_item_id":55,"new_price":1723.0,"update_at":"2023-04-06 22:35:30"},{"commodity_item_id":14,"new_price":7848.0,"update_at":"2023-10-21 02:44:47"},{"commodity_item_id":67,"new_price":1213.0,"update_at":"2023-06-21 04:22:11"},{"commodity_item_id":52,"new_price":329.0,"update_at":"2023-05-05 03:55:41"},{"commodity_item_id":24,"new_price":366.0,"update_at":"2023-07-23 20:49:52"},{"commodity_item_id":32,"new_price":8278.0,"update_at":"2023-02-22 03:37:25"},{"commodity_item_id":94,"new_price":8038.0,"update_at":"2023-11-16 21:02:25"},{"commodity_item_id":19,"new_price":1659.0,"update_at":"2023-05-10 00:15:56"},{"commodity_item_id":97,"new_price":5636.0,"update_at":"2023-07-15 09:49:50"},{"commodity_item_id":41,"new_price":7213.0,"update_at":"2023-11-12 22:28:42"},{"commodity_item_id":62,"new_price":5901.0,"update_at":"2023-03-23 08:03:35"},{"commodity_item_id":89,"new_price":8827.0,"update_at":"2023-09-08 14:38:25"},{"commodity_item_id":35,"new_price":9335.0,"update_at":"2023-10-23 00:55:12"},{"commodity_item_id":20,"new_price":2058.0,"update_at":"2023-07-22 17:25:44"},{"commodity_item_id":71,"new_price":4576.0,"update_at":"2023-05-29 13:51:55"},{"commodity_item_id":26,"new_price":650.0,"update_at":"2023-02-02 08:32:55"},{"commodity_item_id":52,"new_price":2078.0,"update_at":"2023-10-23 00:45:57"},{"commodity_item_id":25,"new_price":2959.0,"update_at":"2023-09-11 08:33:10"},{"commodity_item_id":9,"new_price":5402.0,"update_at":"2023-10-21 15:09:16"},{"commodity_item_id":12,"new_price":1592.0,"update_at":"2023-10-31 07:16:11"},{"commodity_item_id":24,"new_price":576.0,"update_at":"2023-03-10 15:57:42"},{"commodity_item_id":50,"new_price":6669.0,"update_at":"2023-08-16 03:51:18"},{"commodity_item_id":35,"new_price":1927.0,"update_at":"2023-04-09 09:38:16"},{"commodity_item_id":79,"new_price":9991.0,"update_at":"2023-11-23 05:50:42"},{"commodity_item_id":42,"new_price":5545.0,"update_at":"2023-03-28 17:52:13"},{"commodity_item_id":80,"new_price":4839.0,"update_at":"2023-03-17 18:55:27"},{"commodity_item_id":22,"new_price":8417.0,"update_at":"2023-10-07 20:45:12"},{"commodity_item_id":69,"new_price":8119.0,"update_at":"2023-09-28 20:17:38"},{"commodity_item_id":8,"new_price":4550.0,"update_at":"2023-02-05 23:10:43"},{"commodity_item_id":39,"new_price":8930.0,"update_at":"2023-09-26 20:36:48"},{"commodity_item_id":20,"new_price":5325.0,"update_at":"2023-11-01 03:17:11"},{"commodity_item_id":52,"new_price":9852.0,"update_at":"2023-08-13 03:31:54"},{"commodity_item_id":99,"new_price":2631.0,"update_at":"2023-04-20 00:33:31"},{"commodity_item_id":43,"new_price":4991.0,"update_at":"2023-01-14 04:49:29"},{"commodity_item_id":69,"new_price":7430.0,"update_at":"2023-07-25 13:42:25"},{"commodity_item_id":23,"new_price":7425.0,"update_at":"2023-05-31 19:51:24"},{"commodity_item_id":6,"new_price":4318.0,"update_at":"2023-06-02 23:43:21"},{"commodity_item_id":74,"new_price":2635.0,"update_at":"2023-03-08 04:42:20"},{"commodity_item_id":73,"new_price":4343.0,"update_at":"2023-01-24 11:35:06"},{"commodity_item_id":37,"new_price":2389.0,"update_at":"2023-05-25 02:40:30"},{"commodity_item_id":51,"new_price":8157.0,"update_at":"2023-07-09 06:35:59"},{"commodity_item_id":88,"new_price":3042.0,"update_at":"2023-08-14 11:21:11"},{"commodity_item_id":46,"new_price":8382.0,"update_at":"2023-08-19 14:31:35"},{"commodity_item_id":91,"new_price":6716.0,"update_at":"2023-01-17 11:58:49"},{"commodity_item_id":26,"new_price":9306.0,"update_at":"2023-08-20 07:34:24"},{"commodity_item_id":12,"new_price":9647.0,"update_at":"2023-11-04 10:33:04"},{"commodity_item_id":6,"new_price":6622.0,"update_at":"2023-10-04 23:57:14"},{"commodity_item_id":65,"new_price":2423.0,"update_at":"2023-01-26 22:30:09"},{"commodity_item_id":10,"new_price":7052.0,"update_at":"2023-11-01 15:12:50"},{"commodity_item_id":93,"new_price":8216.0,"update_at":"2023-02-10 22:09:08"},{"commodity_item_id":43,"new_price":9990.0,"update_at":"2023-08-16 00:21:10"},{"commodity_item_id":94,"new_price":9958.0,"update_at":"2023-04-14 00:00:59"},{"commodity_item_id":14,"new_price":8190.0,"update_at":"2023-05-16 16:15:23"},{"commodity_item_id":86,"new_price":5226.0,"update_at":"2023-08-27 02:28:42"},{"commodity_item_id":20,"new_price":1523.0,"update_at":"2023-07-04 10:11:54"},{"commodity_item_id":54,"new_price":9689.0,"update_at":"2023-02-16 13:48:00"},{"commodity_item_id":10,"new_price":9677.0,"update_at":"2023-03-06 15:16:24"},{"commodity_item_id":57,"new_price":3305.0,"update_at":"2023-02-16 21:49:37"},{"commodity_item_id":67,"new_price":8294.0,"update_at":"2023-06-11 20:21:52"},{"commodity_item_id":92,"new_price":8293.0,"update_at":"2023-05-15 12:58:12"},{"commodity_item_id":9,"new_price":6754.0,"update_at":"2023-05-06 13:27:59"},{"commodity_item_id":46,"new_price":1711.0,"update_at":"2023-01-17 21:11:42"},{"commodity_item_id":8,"new_price":971.0,"update_at":"2023-10-27 18:08:36"},{"commodity_item_id":64,"new_price":3086.0,"update_at":"2023-01-04 07:34:25"},{"commodity_item_id":32,"new_price":9794.0,"update_at":"2023-08-19 12:34:51"},{"commodity_item_id":73,"new_price":6489.0,"update_at":"2023-11-24 18:42:31"},{"commodity_item_id":36,"new_price":5090.0,"update_at":"2023-07-04 14:03:39"},{"commodity_item_id":15,"new_price":7751.0,"update_at":"2023-10-25 01:46:02"},{"commodity_item_id":9,"new_price":1382.0,"update_at":"2023-07-20 02:31:39"},{"commodity_item_id":87,"new_price":7156.0,"update_at":"2023-11-26 19:40:25"},{"commodity_item_id":1,"new_price":155.0,"update_at":"2023-07-16 03:24:15"},{"commodity_item_id":50,"new_price":9814.0,"update_at":"2023-08-15 12:31:44"},{"commodity_item_id":26,"new_price":6067.0,"update_at":"2023-08-16 00:04:08"},{"commodity_item_id":86,"new_price":809.0,"update_at":"2023-06-29 10:15:38"},{"commodity_item_id":16,"new_price":976.0,"update_at":"2023-04-30 09:40:30"},{"commodity_item_id":8,"new_price":6997.0,"update_at":"2023-08-04 23:01:06"},{"commodity_item_id":86,"new_price":9811.0,"update_at":"2023-08-08 09:40:50"},{"commodity_item_id":18,"new_price":6634.0,"update_at":"2023-10-25 16:32:29"},{"commodity_item_id":63,"new_price":8016.0,"update_at":"2023-05-27 01:09:44"},{"commodity_item_id":13,"new_price":3109.0,"update_at":"2023-10-15 07:44:00"},{"commodity_item_id":4,"new_price":8670.0,"update_at":"2023-08-28 02:16:56"},{"commodity_item_id":94,"new_price":9608.0,"update_at":"2023-11-07 07:08:40"},{"commodity_item_id":75,"new_price":6814.0,"update_at":"2023-09-09 10:44:13"},{"commodity_item_id":94,"new_price":6401.0,"update_at":"2023-11-25 07:42:00"},{"commodity_item_id":73,"new_price":3291.0,"update_at":"2023-08-29 00:27:15"},{"commodity_item_id":21,"new_price":198.0,"update_at":"2023-11-16 04:42:32"},{"commodity_item_id":97,"new_price":3969.0,"update_at":"2023-05-02 09:45:06"},{"commodity_item_id":79,"new_price":3509.0,"update_at":"2023-05-07 04:34:55"},{"commodity_item_id":8,"new_price":2156.0,"update_at":"2023-07-28 14:28:29"},{"commodity_item_id":26,"new_price":6635.0,"update_at":"2023-10-31 14:20:15"},{"commodity_item_id":27,"new_price":623.0,"update_at":"2023-07-16 06:53:04"},{"commodity_item_id":34,"new_price":7418.0,"update_at":"2023-07-09 03:37:07"},{"commodity_item_id":2,"new_price":1054.0,"update_at":"2023-09-18 19:49:41"},{"commodity_item_id":21,"new_price":3501.0,"update_at":"2023-11-20 22:01:29"},{"commodity_item_id":67,"new_price":1475.0,"update_at":"2023-07-28 02:36:47"},{"commodity_item_id":92,"new_price":8283.0,"update_at":"2023-08-31 18:26:01"},{"commodity_item_id":47,"new_price":3043.0,"update_at":"2023-02-19 20:57:36"},{"commodity_item_id":71,"new_price":3637.0,"update_at":"2023-09-05 13:51:20"},{"commodity_item_id":37,"new_price":752.0,"update_at":"2023-05-10 06:44:37"},{"commodity_item_id":14,"new_price":8201.0,"update_at":"2023-03-07 20:21:04"},{"commodity_item_id":73,"new_price":7998.0,"update_at":"2023-07-05 00:57:19"},{"commodity_item_id":89,"new_price":4616.0,"update_at":"2023-02-11 20:11:19"},{"commodity_item_id":61,"new_price":2224.0,"update_at":"2023-11-01 04:18:52"},{"commodity_item_id":15,"new_price":2002.0,"update_at":"2023-03-23 14:55:05"},{"commodity_item_id":21,"new_price":9641.0,"update_at":"2023-05-24 02:56:55"},{"commodity_item_id":44,"new_price":163.0,"update_at":"2023-01-07 07:20:19"},{"commodity_item_id":94,"new_price":9428.0,"update_at":"2023-11-19 19:51:03"},{"commodity_item_id":99,"new_price":9011.0,"update_at":"2023-10-14 09:24:21"},{"commodity_item_id":7,"new_price":4996.0,"update_at":"2023-01-28 04:05:54"},{"commodity_item_id":33,"new_price":731.0,"update_at":"2023-07-22 07:58:36"},{"commodity_item_id":90,"new_price":4289.0,"update_at":"2023-11-13 03:23:40"},{"commodity_item_id":78,"new_price":8255.0,"update_at":"2023-02-22 07:58:48"},{"commodity_item_id":32,"new_price":768.0,"update_at":"2023-02-06 04:04:32"},{"commodity_item_id":2,"new_price":3010.0,"update_at":"2023-06-18 11:33:22"},{"commodity_item_id":57,"new_price":2478.0,"update_at":"2023-08-07 23:33:02"},{"commodity_item_id":1,"new_price":3172.0,"update_at":"2023-05-20 12:05:50"},{"commodity_item_id":24,"new_price":9324.0,"update_at":"2023-02-02 11:12:30"},{"commodity_item_id":66,"new_price":1751.0,"update_at":"2023-09-18 02:21:14"},{"commodity_item_id":17,"new_price":7226.0,"update_at":"2023-03-02 23:37:31"},{"commodity_item_id":22,"new_price":287.0,"update_at":"2023-07-11 07:30:32"},{"commodity_item_id":38,"new_price":6798.0,"update_at":"2023-06-11 14:23:22"},{"commodity_item_id":42,"new_price":1148.0,"update_at":"2023-01-22 02:03:51"},{"commodity_item_id":8,"new_price":7880.0,"update_at":"2023-06-09 13:32:38"},{"commodity_item_id":25,"new_price":3942.0,"update_at":"2023-05-17 19:28:29"},{"commodity_item_id":53,"new_price":1898.0,"update_at":"2023-10-10 18:53:50"},{"commodity_item_id":41,"new_price":6495.0,"update_at":"2023-11-06 17:35:23"},{"commodity_item_id":28,"new_price":734.0,"update_at":"2023-07-21 12:06:13"},{"commodity_item_id":58,"new_price":7379.0,"update_at":"2023-10-08 17:37:08"},{"commodity_item_id":38,"new_price":6623.0,"update_at":"2023-09-16 04:53:59"},{"commodity_item_id":92,"new_price":3527.0,"update_at":"2023-08-04 06:31:59"},{"commodity_item_id":75,"new_price":3721.0,"update_at":"2023-03-07 01:36:32"},{"commodity_item_id":91,"new_price":1595.0,"update_at":"2023-02-09 00:50:28"},{"commodity_item_id":86,"new_price":4822.0,"update_at":"2023-10-27 19:22:13"},{"commodity_item_id":74,"new_price":6449.0,"update_at":"2023-08-21 02:31:51"},{"commodity_item_id":35,"new_price":4061.0,"update_at":"2023-09-03 18:15:59"},{"commodity_item_id":88,"new_price":2194.0,"update_at":"2023-11-21 11:21:07"},{"commodity_item_id":76,"new_price":2250.0,"update_at":"2023-06-02 09:14:49"},{"commodity_item_id":90,"new_price":7538.0,"update_at":"2023-01-18 11:48:13"},{"commodity_item_id":77,"new_price":3759.0,"update_at":"2023-04-24 17:18:55"},{"commodity_item_id":99,"new_price":5205.0,"update_at":"2023-10-27 00:35:27"},{"commodity_item_id":12,"new_price":6718.0,"update_at":"2023-06-06 22:41:41"},{"commodity_item_id":60,"new_price":8036.0,"update_at":"2023-07-12 20:37:15"},{"commodity_item_id":19,"new_price":7086.0,"update_at":"2023-08-25 09:39:05"},{"commodity_item_id":65,"new_price":5942.0,"update_at":"2023-04-07 20:53:29"},{"commodity_item_id":42,"new_price":8348.0,"update_at":"2023-08-02 00:39:54"},{"commodity_item_id":72,"new_price":1996.0,"update_at":"2023-09-17 16:15:08"},{"commodity_item_id":21,"new_price":1280.0,"update_at":"2023-06-29 03:59:20"},{"commodity_item_id":100,"new_price":8445.0,"update_at":"2023-03-11 06:00:59"},{"commodity_item_id":14,"new_price":4211.0,"update_at":"2023-08-13 15:44:38"},{"commodity_item_id":91,"new_price":4563.0,"update_at":"2023-07-17 12:01:23"},{"commodity_item_id":83,"new_price":1089.0,"update_at":"2023-07-28 12:11:00"},{"commodity_item_id":7,"new_price":5093.0,"update_at":"2023-07-05 19:03:56"},{"commodity_item_id":28,"new_price":4515.0,"update_at":"2023-02-13 10:28:28"},{"commodity_item_id":6,"new_price":1026.0,"update_at":"2023-09-11 18:35:06"},{"commodity_item_id":27,"new_price":9310.0,"update_at":"2023-10-16 13:58:07"},{"commodity_item_id":1,"new_price":4194.0,"update_at":"2023-11-10 14:48:02"},{"commodity_item_id":85,"new_price":8908.0,"update_at":"2023-03-16 11:13:42"},{"commodity_item_id":86,"new_price":5516.0,"update_at":"2023-06-25 16:24:49"},{"commodity_item_id":23,"new_price":4478.0,"update_at":"2023-09-08 21:32:51"},{"commodity_item_id":75,"new_price":2210.0,"update_at":"2023-09-07 21:45:27"},{"commodity_item_id":85,"new_price":8906.0,"update_at":"2023-03-23 23:27:19"},{"commodity_item_id":3,"new_price":3378.0,"update_at":"2023-05-25 03:03:33"},{"commodity_item_id":16,"new_price":644.0,"update_at":"2023-02-19 23:41:14"},{"commodity_item_id":64,"new_price":1975.0,"update_at":"2023-03-18 21:34:55"},{"commodity_item_id":42,"new_price":7760.0,"update_at":"2023-07-22 15:22:03"},{"commodity_item_id":51,"new_price":8188.0,"update_at":"2023-06-26 12:22:43"},{"commodity_item_id":58,"new_price":5758.0,"update_at":"2023-10-02 21:34:52"},{"commodity_item_id":97,"new_price":3412.0,"update_at":"2023-01-30 02:10:58"},{"commodity_item_id":82,"new_price":8984.0,"update_at":"2023-03-03 05:41:59"},{"commodity_item_id":39,"new_price":5130.0,"update_at":"2023-11-26 10:38:19"},{"commodity_item_id":28,"new_price":5636.0,"update_at":"2023-01-24 23:36:24"},{"commodity_item_id":28,"new_price":1206.0,"update_at":"2023-05-07 03:25:57"},{"commodity_item_id":26,"new_price":3694.0,"update_at":"2023-10-19 04:46:00"},{"commodity_item_id":61,"new_price":1147.0,"update_at":"2023-05-16 22:13:05"},{"commodity_item_id":98,"new_price":3889.0,"update_at":"2023-06-09 07:40:28"},{"commodity_item_id":89,"new_price":8465.0,"update_at":"2023-10-31 20:43:49"},{"commodity_item_id":6,"new_price":5047.0,"update_at":"2023-09-15 05:20:29"},{"commodity_item_id":90,"new_price":6017.0,"update_at":"2023-05-24 00:49:23"},{"commodity_item_id":72,"new_price":18.0,"update_at":"2023-09-14 20:27:36"},{"commodity_item_id":85,"new_price":4259.0,"update_at":"2023-01-26 04:49:35"},{"commodity_item_id":28,"new_price":558.0,"update_at":"2023-11-07 07:33:01"},{"commodity_item_id":22,"new_price":9176.0,"update_at":"2023-01-26 17:01:55"},{"commodity_item_id":72,"new_price":8107.0,"update_at":"2023-05-28 08:34:18"},{"commodity_item_id":49,"new_price":9321.0,"update_at":"2023-08-25 23:47:10"},{"commodity_item_id":49,"new_price":5912.0,"update_at":"2023-04-14 03:04:49"},{"commodity_item_id":65,"new_price":1526.0,"update_at":"2023-07-18 00:46:04"},{"commodity_item_id":44,"new_price":7428.0,"update_at":"2023-05-01 09:07:33"},{"commodity_item_id":48,"new_price":724.0,"update_at":"2023-09-28 22:00:05"},{"commodity_item_id":16,"new_price":9709.0,"update_at":"2023-09-28 09:22:14"},{"commodity_item_id":99,"new_price":1329.0,"update_at":"2023-07-28 17:30:09"},{"commodity_item_id":55,"new_price":8218.0,"update_at":"2023-11-04 05:26:28"},{"commodity_item_id":34,"new_price":2404.0,"update_at":"2023-03-27 09:55:45"},{"commodity_item_id":70,"new_price":4899.0,"update_at":"2023-09-06 00:57:52"},{"commodity_item_id":43,"new_price":4188.0,"update_at":"2023-10-28 10:20:11"},{"commodity_item_id":29,"new_price":8378.0,"update_at":"2023-05-15 07:35:39"},{"commodity_item_id":62,"new_price":2689.0,"update_at":"2023-07-23 20:28:38"},{"commodity_item_id":13,"new_price":7084.0,"update_at":"2023-04-29 01:43:19"},{"commodity_item_id":24,"new_price":2392.0,"update_at":"2023-04-06 17:18:18"},{"commodity_item_id":4,"new_price":211.0,"update_at":"2023-02-22 04:29:09"},{"commodity_item_id":52,"new_price":6969.0,"update_at":"2023-03-24 08:17:14"},{"commodity_item_id":58,"new_price":7388.0,"update_at":"2023-01-30 01:24:26"},{"commodity_item_id":62,"new_price":4949.0,"update_at":"2023-09-27 05:28:33"},{"commodity_item_id":95,"new_price":177.0,"update_at":"2023-11-13 15:08:38"},{"commodity_item_id":13,"new_price":5344.0,"update_at":"2023-11-11 15:45:32"},{"commodity_item_id":13,"new_price":5403.0,"update_at":"2023-11-01 03:47:03"},{"commodity_item_id":75,"new_price":2998.0,"update_at":"2023-02-25 23:01:55"},{"commodity_item_id":57,"new_price":273.0,"update_at":"2023-03-04 14:45:16"},{"commodity_item_id":69,"new_price":5201.0,"update_at":"2023-10-16 04:10:43"},{"commodity_item_id":63,"new_price":6991.0,"update_at":"2023-08-21 06:38:45"},{"commodity_item_id":21,"new_price":7717.0,"update_at":"2023-07-20 06:55:21"},{"commodity_item_id":58,"new_price":9739.0,"update_at":"2023-03-28 12:14:34"},{"commodity_item_id":51,"new_price":4772.0,"update_at":"2023-09-03 04:39:00"},{"commodity_item_id":85,"new_price":5260.0,"update_at":"2023-01-12 08:50:39"},{"commodity_item_id":55,"new_price":2185.0,"update_at":"2023-03-06 15:00:39"},{"commodity_item_id":73,"new_price":4222.0,"update_at":"2023-02-08 03:03:28"},{"commodity_item_id":72,"new_price":6721.0,"update_at":"2023-01-10 19:30:47"},{"commodity_item_id":27,"new_price":9998.0,"update_at":"2023-11-26 08:56:56"},{"commodity_item_id":93,"new_price":3242.0,"update_at":"2023-07-06 20:10:13"},{"commodity_item_id":6,"new_price":5976.0,"update_at":"2023-02-01 22:44:41"},{"commodity_item_id":18,"new_price":4812.0,"update_at":"2023-11-16 16:43:51"},{"commodity_item_id":93,"new_price":3949.0,"update_at":"2023-11-14 18:52:52"},{"commodity_item_id":18,"new_price":659.0,"update_at":"2023-10-21 19:08:20"},{"commodity_item_id":11,"new_price":6429.0,"update_at":"2023-03-26 12:44:09"},{"commodity_item_id":52,"new_price":8155.0,"update_at":"2023-03-02 23:46:49"},{"commodity_item_id":72,"new_price":1818.0,"update_at":"2023-09-05 01:51:51"},{"commodity_item_id":53,"new_price":3544.0,"update_at":"2023-03-21 14:02:20"},{"commodity_item_id":26,"new_price":8178.0,"update_at":"2023-07-12 10:38:47"},{"commodity_item_id":63,"new_price":1354.0,"update_at":"2023-03-10 06:59:07"},{"commodity_item_id":80,"new_price":3912.0,"update_at":"2023-04-30 02:20:44"},{"commodity_item_id":5,"new_price":5091.0,"update_at":"2023-06-14 07:46:30"},{"commodity_item_id":44,"new_price":6367.0,"update_at":"2023-01-16 19:31:00"},{"commodity_item_id":52,"new_price":9573.0,"update_at":"2023-01-24 08:55:07"},{"commodity_item_id":58,"new_price":408.0,"update_at":"2023-06-05 12:14:29"},{"commodity_item_id":65,"new_price":5919.0,"update_at":"2023-01-26 12:10:40"},{"commodity_item_id":1,"new_price":3599.0,"update_at":"2023-06-27 01:51:43"},{"commodity_item_id":50,"new_price":3001.0,"update_at":"2023-09-07 05:08:37"},{"commodity_item_id":50,"new_price":4630.0,"update_at":"2023-03-04 21:27:31"},{"commodity_item_id":59,"new_price":1714.0,"update_at":"2023-02-05 11:55:07"},{"commodity_item_id":41,"new_price":9591.0,"update_at":"2023-02-08 23:41:10"},{"commodity_item_id":11,"new_price":3067.0,"update_at":"2023-02-08 16:21:35"},{"commodity_item_id":84,"new_price":9905.0,"update_at":"2023-07-03 22:16:46"},{"commodity_item_id":65,"new_price":1216.0,"update_at":"2023-11-03 12:07:18"},{"commodity_item_id":91,"new_price":9808.0,"update_at":"2023-04-23 21:16:15"},{"commodity_item_id":46,"new_price":2038.0,"update_at":"2023-04-01 21:45:55"},{"commodity_item_id":38,"new_price":140.0,"update_at":"2023-08-04 20:58:54"},{"commodity_item_id":22,"new_price":8374.0,"update_at":"2023-10-04 11:27:05"},{"commodity_item_id":7,"new_price":618.0,"update_at":"2023-02-28 22:39:16"},{"commodity_item_id":97,"new_price":1215.0,"update_at":"2023-11-24 14:56:07"},{"commodity_item_id":26,"new_price":6146.0,"update_at":"2023-05-06 00:55:36"},{"commodity_item_id":41,"new_price":5011.0,"update_at":"2023-02-08 18:13:24"},{"commodity_item_id":71,"new_price":7151.0,"update_at":"2023-03-30 13:51:48"},{"commodity_item_id":62,"new_price":9950.0,"update_at":"2023-01-24 02:06:56"},{"commodity_item_id":72,"new_price":5714.0,"update_at":"2023-05-24 15:31:26"},{"commodity_item_id":63,"new_price":6004.0,"update_at":"2023-01-29 08:03:00"},{"commodity_item_id":50,"new_price":4583.0,"update_at":"2023-11-10 15:54:34"},{"commodity_item_id":30,"new_price":3845.0,"update_at":"2023-01-01 01:26:50"},{"commodity_item_id":97,"new_price":7292.0,"update_at":"2023-10-02 11:01:34"},{"commodity_item_id":53,"new_price":8241.0,"update_at":"2023-08-13 23:52:41"},{"commodity_item_id":59,"new_price":4217.0,"update_at":"2023-10-11 11:16:13"},{"commodity_item_id":15,"new_price":836.0,"update_at":"2023-05-31 11:25:31"},{"commodity_item_id":70,"new_price":240.0,"update_at":"2023-05-27 13:28:38"},{"commodity_item_id":98,"new_price":2959.0,"update_at":"2023-03-23 01:14:47"},{"commodity_item_id":18,"new_price":6926.0,"update_at":"2023-11-01 05:18:39"},{"commodity_item_id":71,"new_price":2114.0,"update_at":"2023-07-04 01:59:47"},{"commodity_item_id":90,"new_price":4347.0,"update_at":"2023-02-03 19:38:19"},{"commodity_item_id":65,"new_price":2943.0,"update_at":"2023-07-12 22:32:03"},{"commodity_item_id":81,"new_price":8886.0,"update_at":"2023-05-07 05:35:33"},{"commodity_item_id":66,"new_price":3816.0,"update_at":"2023-10-29 10:26:06"},{"commodity_item_id":4,"new_price":4204.0,"update_at":"2023-11-21 23:27:39"},{"commodity_item_id":43,"new_price":6277.0,"update_at":"2023-08-25 08:21:08"},{"commodity_item_id":79,"new_price":813.0,"update_at":"2023-06-08 00:07:01"},{"commodity_item_id":63,"new_price":199.0,"update_at":"2023-02-14 21:30:33"},{"commodity_item_id":29,"new_price":2708.0,"update_at":"2023-10-01 03:59:52"},{"commodity_item_id":36,"new_price":7318.0,"update_at":"2023-03-11 14:05:35"},{"commodity_item_id":42,"new_price":4494.0,"update_at":"2023-09-11 17:40:08"},{"commodity_item_id":16,"new_price":6210.0,"update_at":"2023-04-13 21:36:00"},{"commodity_item_id":46,"new_price":4443.0,"update_at":"2023-01-20 11:51:48"},{"commodity_item_id":58,"new_price":99.0,"update_at":"2023-11-16 15:52:16"},{"commodity_item_id":67,"new_price":493.0,"update_at":"2023-09-21 14:52:34"},{"commodity_item_id":45,"new_price":6445.0,"update_at":"2023-08-24 04:14:22"},{"commodity_item_id":27,"new_price":2571.0,"update_at":"2023-08-26 18:47:08"},{"commodity_item_id":69,"new_price":1054.0,"update_at":"2023-06-24 15:05:49"},{"commodity_item_id":54,"new_price":5134.0,"update_at":"2023-05-25 02:31:22"},{"commodity_item_id":32,"new_price":8898.0,"update_at":"2023-04-23 12:32:31"},{"commodity_item_id":29,"new_price":9876.0,"update_at":"2023-02-20 00:36:20"},{"commodity_item_id":36,"new_price":5681.0,"update_at":"2023-06-25 21:40:04"},{"commodity_item_id":26,"new_price":4127.0,"update_at":"2023-10-10 09:48:37"},{"commodity_item_id":19,"new_price":1838.0,"update_at":"2023-05-19 13:03:38"},{"commodity_item_id":64,"new_price":5994.0,"update_at":"2023-05-16 01:28:11"},{"commodity_item_id":81,"new_price":4180.0,"update_at":"2023-01-26 23:41:04"},{"commodity_item_id":63,"new_price":539.0,"update_at":"2023-05-17 01:19:35"},{"commodity_item_id":29,"new_price":5580.0,"update_at":"2023-11-05 07:50:12"},{"commodity_item_id":81,"new_price":5843.0,"update_at":"2023-04-21 20:51:28"},{"commodity_item_id":69,"new_price":4922.0,"update_at":"2023-09-16 19:14:15"},{"commodity_item_id":92,"new_price":1363.0,"update_at":"2023-01-14 22:08:20"},{"commodity_item_id":56,"new_price":8590.0,"update_at":"2023-07-31 17:10:04"},{"commodity_item_id":29,"new_price":2238.0,"update_at":"2023-11-25 14:33:06"},{"commodity_item_id":59,"new_price":6922.0,"update_at":"2023-03-05 04:31:31"},{"commodity_item_id":47,"new_price":1730.0,"update_at":"2023-09-07 06:17:00"},{"commodity_item_id":7,"new_price":6603.0,"update_at":"2023-07-30 09:21:48"},{"commodity_item_id":22,"new_price":2855.0,"update_at":"2023-10-27 20:58:09"},{"commodity_item_id":25,"new_price":9196.0,"update_at":"2023-06-01 09:33:14"},{"commodity_item_id":1,"new_price":359.0,"update_at":"2023-03-11 14:25:15"},{"commodity_item_id":91,"new_price":4636.0,"update_at":"2023-11-13 18:02:23"},{"commodity_item_id":65,"new_price":6697.0,"update_at":"2023-02-17 01:51:43"},{"commodity_item_id":79,"new_price":6106.0,"update_at":"2023-09-18 09:28:12"},{"commodity_item_id":8,"new_price":9564.0,"update_at":"2023-02-20 14:18:25"},{"commodity_item_id":2,"new_price":2233.0,"update_at":"2023-06-07 08:17:14"},{"commodity_item_id":38,"new_price":8183.0,"update_at":"2023-05-08 01:12:19"},{"commodity_item_id":96,"new_price":2316.0,"update_at":"2023-03-22 07:23:32"},{"commodity_item_id":26,"new_price":5025.0,"update_at":"2023-05-24 18:12:26"},{"commodity_item_id":16,"new_price":5323.0,"update_at":"2023-04-16 15:57:57"},{"commodity_item_id":35,"new_price":4389.0,"update_at":"2023-08-30 15:42:10"}]